speedml/__init__.py
speedml/base.py
speedml/feature.py
speedml/model.py
speedml/plot.py
speedml/util.py
speedml/xgb.py
speedml-0.9.3.dist-info/DESCRIPTION.rst
speedml-0.9.3.dist-info/METADATA
speedml-0.9.3.dist-info/RECORD
speedml-0.9.3.dist-info/WHEEL
speedml-0.9.3.dist-info/metadata.json
speedml-0.9.3.dist-info/top_level.txt
